setup.py
tests/__init__.py
tests/test_apscheduler.py
zwb_job/__init__.py
zwb_job/apscheduler_utils.py
zwb_job.egg-info/PKG-INFO
zwb_job.egg-info/SOURCES.txt
zwb_job.egg-info/dependency_links.txt
zwb_job.egg-info/requires.txt
zwb_job.egg-info/top_level.txt