Metadata-Version: 1.0
Name: zwb-job
Version: 1.0.0
Summary: zwb_job
Home-page: https://github.com/weibin268/zwb_job
Author: zhuang weibin
Author-email: 448075543@qq.com
License: UNKNOWN
Keywords: util
Platform: any
